datapungi/__init__.py
datapungi-0.1.dist-info/LICENSE
datapungi-0.1.dist-info/WHEEL
datapungi-0.1.dist-info/METADATA
datapungi-0.1.dist-info/RECORD
