Metadata-Version: 2.1
Name: datapungi
Version: 0.1
Summary: Connects to API drivers
Home-page: UNKNOWN
License: UNKNOWN
Author: James Otterson
Author-email: jjotterson@gmail.com
Classifier: Development Status :: 4 - Beta
Classifier: Intended Audience :: Developers
Classifier: Intended Audience :: Science/Research
Classifier: Programming Language :: Python
Requires-Dist: requests
Requires-Dist: pandas
Requires-Dist: pytest
Requires-Dist: pytest-html
Requires-Dist: pyperclip
Requires-Dist: lxml
Requires-Dist: xlrd
Requires-Dist: beautifulsoup4
Requires-Dist: html5lib
